backlogapiprocessmodule/__init__.py
backlogapiprocessmodule/backlogapiprocess.py
backlogapiprocessmodule/models/__init__.py
backlogapiprocessmodule/models/markdown_model.py
backlogapiprocessmodule/utils/AppManager.py
backlogapiprocessmodule/utils/Config.py
backlogapiprocessmodule/utils/Detail.py
backlogapiprocessmodule/utils/Issue.py
backlogapiprocessmodule/utils/Logger.py
backlogapiprocessmodule/utils/Project.py
backlogapiprocessmodule/utils/Summary.py
backlogapiprocessmodule/utils/WikiBase.py
backlogapiprocessmodule/utils/__init__.py
backlogapiprocessmodule/utils/config_util.py
backlogapiprocessmodule/utils/count_actual_hours_util.py
backlogapiprocessmodule/utils/issue_type_util.py
backlogapiprocessmodule/utils/issue_util.py
backlogapiprocessmodule/utils/log_util.py
backlogapiprocessmodule/utils/process_project_util.py
backlogapiprocessmodule/utils/term_util.py
backlogapiprocessmodule/utils/time_utils.py
backlogapiprocessmodule/utils/wiki_util.py
backlogprocessing-0.1.7.dist-info/LICENSE
backlogprocessing-0.1.7.dist-info/METADATA
backlogprocessing-0.1.7.dist-info/WHEEL
backlogprocessing-0.1.7.dist-info/top_level.txt
backlogprocessing-0.1.7.dist-info/RECORD
