Metadata-Version: 2.1
Name: backlogprocessing
Version: 0.1.7
Summary: processing working time on backlog.
Home-page: https://github.com/tys-hiroshi/backlogprocessing
Author: Hiroshi Tashiro
License: MIT
Platform: UNKNOWN
Requires-Dist: PyYAML
Requires-Dist: azure-functions
Requires-Dist: chardet
Requires-Dist: python-dateutil
Requires-Dist: jmespath
Requires-Dist: pybacklog
Requires-Dist: pytz
Requires-Dist: ruamel.appconfig
Requires-Dist: ruamel.std.argparse
Requires-Dist: zope.interface
Requires-Dist: typed-ast
